<?xml version="1.0" encoding="utf-8"?><BlockProgram xmlns:xsi="http://www.w3.org/2001/XMLSchema-instance" xmlns:xsd="http://www.w3.org/2001/XMLSchema"><internal_tags_list><ArrayOfTag><Tag><tag_UID>21</tag_UID><tag_name>Tag1</tag_name><Datatype>Bool</Datatype><value>false</value><Mode>Input</Mode><Scope>LocalVariable</Scope><Accessibility>Public</Accessibility></Tag><Tag><tag_UID>22</tag_UID><tag_name>Tag2</tag_name><Datatype>Bool</Datatype><value>false</value><Mode>Input</Mode><Scope>LocalVariable</Scope><Accessibility>Public</Accessibility></Tag></ArrayOfTag><ArrayOfTag><Tag><tag_UID>24</tag_UID><tag_name>Tag4</tag_name><Datatype>Bool</Datatype><value>false</value><Mode>Output</Mode><Scope>LocalVariable</Scope><Accessibility>Public</Accessibility></Tag></ArrayOfTag><ArrayOfTag><Tag><tag_UID>23</tag_UID><tag_name>Tag3</tag_name><Datatype>Bool</Datatype><value>false</value><Mode>InOut</Mode><Scope>LocalVariable</Scope><Accessibility>Public</Accessibility></Tag></ArrayOfTag><ArrayOfTag /></internal_tags_list><networks_list><Network><and><or_list><Or><Contact_List><Contact><tag><tag_UID>21</tag_UID><tag_name>Tag1</tag_name><Datatype>Bool</Datatype><value>false</value><Mode>Input</Mode><Scope>LocalVariable</Scope><Accessibility>Public</Accessibility></tag><Contact_UId>25</Contact_UId><Contact_Type>Contact</Contact_Type><negated>false</negated><powerrail>true</powerrail><wire_out_UId>28</wire_out_UId></Contact><Contact><tag><tag_UID>22</tag_UID><tag_name>Tag2</tag_name><Datatype>Bool</Datatype><value>false</value><Mode>Input</Mode><Scope>LocalVariable</Scope><Accessibility>Public</Accessibility></tag><Contact_UId>26</Contact_UId><Contact_Type>Contact</Contact_Type><negated>false</negated><powerrail>true</powerrail><wire_out_UId>28</wire_out_UId></Contact></Contact_List></Or></or_list><Contact_List><Contact><tag><tag_UID>23</tag_UID><tag_name>Tag3</tag_name><Datatype>Bool</Datatype><value>false</value><Mode>InOut</Mode><Scope>LocalVariable</Scope><Accessibility>Public</Accessibility></tag><Contact_UId>28</Contact_UId><Contact_Type>Contact</Contact_Type><negated>true</negated><powerrail>false</powerrail><wire_out_UId>29</wire_out_UId></Contact><Contact><tag><tag_UID>24</tag_UID><tag_name>Tag4</tag_name><Datatype>Bool</Datatype><value>false</value><Mode>Output</Mode><Scope>LocalVariable</Scope><Accessibility>Public</Accessibility></tag><Contact_UId>29</Contact_UId><Contact_Type>Coil</Contact_Type><negated>false</negated><powerrail>false</powerrail></Contact></Contact_List></and></Network></networks_list></BlockProgram>